{"stats":{"total":8,"passed":7,"retries":1,"failed":1},"status":"failed","newTests":[{"id":"046f30f6695f1623bef6e21fc3d56ad5","name":"TC-001: Verify home page is loaded after login","status":"passed","duration":193},{"id":"46dcd73e1213f8796552078b7f7d9b27","name":"TC-004: Navigate to Cameras page","status":"passed","duration":1684},{"id":"374c7c7ba31b3bc40feab09110563566","name":"TC-007: Verify camera names are displayed on Cameras page","status":"passed","duration":826},{"id":"296e40b39d809daa543b5a48cb011e32","name":"TC-002: Arm Home and Disarm partitions","status":"failed","duration":34849},{"id":"071b1461dbf51c4a283b04152e79b81c","name":"TC-002: Arm Home and Disarm partitions","status":"failed","duration":35041},{"id":"bc77d247d1a8a5b8d7be0beeb2135747","name":"TC-005: Navigate to Activity page and verify log","status":"passed","duration":3413},{"id":"e9a41754adc4a2d7f420155657f032d5","name":"TC-008: Verify camera feed sections load on Cameras page","status":"passed","duration":493},{"id":"ddd977fa6e6a8a574491f7c66c982790","name":"TC-003: Navigate to Devices page","status":"passed","duration":3308},{"id":"7e0ba2defd9c1c9645534f9bb439f0c6","name":"TC-006: Verify all cameras are visible on Cameras page","status":"passed","duration":2070},{"id":"51771d15903283f8f51aa854853d83f0","name":"TC-002: Arm Home and Disarm partitions","status":"failed","duration":16058}],"flakyTests":[],"retryTests":[],"name":"Allure Report","duration":47028,"createdAt":1780399744066,"plugin":"Awesome","meta":{"reportId":"d223cda9-a353-456f-b310-8c8ce4f35b5c","singleFile":false,"withTestResultsLinks":true},"pullRequestHref":"","jobHref":"https://github.com/DevKesh/playwright-project-mtech/actions/runs/26816527520"}