{
  "pageName": "DevicesPage",
  "url": "/automation",
  "urlPattern": "**/automation",
  "description": "IoT devices page showing thermostats, locks, switches in expandable categories",
  "elements": {
    "pageHeading": {
      "selector": "page.getByRole('heading', { name: /Devices|Automation/ })",
      "type": "heading",
      "action": "assert",
      "context": "Page heading confirming Devices page loaded",
      "verified": true,
      "brokenSince": "2026-05-14T11:00:52.586Z",
      "verifiedAt": "2026-05-14T11:30:02.833Z"
    },
    "deviceCategories": {
      "selector": "page.locator('.device-category, .automation-card, [class*=device]')",
      "type": "container",
      "action": "assert",
      "context": "Device category cards/sections",
      "verified": false,
      "brokenSince": "2026-05-14T11:30:02.852Z"
    }
  },
  "stateTransitions": {},
  "dataBindings": {},
  "metadata": {
    "lastValidated": "2026-05-14T11:30:02.852Z"
  }
}